README.md
setup.py
service_mapping_plugin_framework/allocate_nssi_abc.py
service_mapping_plugin_framework/deallocate_nssi_abc.py
service_mapping_plugin_framework/settings.py
service_mapping_plugin_framework.egg-info/PKG-INFO
service_mapping_plugin_framework.egg-info/SOURCES.txt
service_mapping_plugin_framework.egg-info/dependency_links.txt
service_mapping_plugin_framework.egg-info/not-zip-safe
service_mapping_plugin_framework.egg-info/requires.txt
service_mapping_plugin_framework.egg-info/top_level.txt