Metadata-Version: 1.0
Name: service-mapping-plugin-framework
Version: 1.1
Summary: Service Mapping Plug-in framework
Home-page: http://github.com/free5gmano/service-mapping-plugin-framework
Author: free5gmano
Author-email: free5gmano@gmail.com
License: Apache
Platform: UNKNOWN
